abram_cryptography.py
abram_cryptography_tools-1.0.1.dist-info/METADATA
abram_cryptography_tools-1.0.1.dist-info/WHEEL
abram_cryptography_tools-1.0.1.dist-info/top_level.txt
abram_cryptography_tools-1.0.1.dist-info/RECORD
