Metadata-Version: 2.4
Name: abram_cryptography_tools
Version: 1.0.1
Summary: A custom cryptography library that turns your text into a secret code
Author: Abram Jindal
Requires-Dist: rich
Dynamic: author
Dynamic: requires-dist
Dynamic: summary
